ccd_logger/__init__.py
ccd_logger/config.py
ccd_logger/logger.py
ccd_logger-0.1.0.dist-info/licenses/LICENSE
ccd_logger-0.1.0.dist-info/METADATA
ccd_logger-0.1.0.dist-info/WHEEL
ccd_logger-0.1.0.dist-info/top_level.txt
ccd_logger-0.1.0.dist-info/RECORD
